easygv/__init__.py
easygv/easygv.py
easygv-0.1.0.dist-info/DESCRIPTION.rst
easygv-0.1.0.dist-info/METADATA
easygv-0.1.0.dist-info/RECORD
easygv-0.1.0.dist-info/WHEEL
easygv-0.1.0.dist-info/entry_points.txt
easygv-0.1.0.dist-info/metadata.json
easygv-0.1.0.dist-info/top_level.txt
