Metadata-Version: 2.0
Name: easygv
Version: 0.1.0
Summary: Define nodes and edges in an excel file and graph-style attributes in a yaml file with inheritence.
Home-page: https://github.com/xguse/easygv
Author: Gus Dunn
Author-email: w.gus.dunn@gmail.com
License: MIT license
Keywords: easygv
Platform: UNKNOWN
Classifier: Development Status :: 2 - Pre-Alpha
Classifier: Intended Audience :: Developers
Classifier: License :: OSI Approved :: MIT License
Classifier: Natural Language :: English
Classifier: Programming Language :: Python :: 3
Classifier: Programming Language :: Python :: 3.4
Classifier: Programming Language :: Python :: 3.5
Classifier: Programming Language :: Python :: 3.6
Requires-Dist: appdirs
Requires-Dist: click
Requires-Dist: graphviz
Requires-Dist: logzero
Requires-Dist: pandas
Requires-Dist: pygraphviz
Requires-Dist: recommonmark
Requires-Dist: ruamel.yaml
Requires-Dist: xlrd
Requires-Dist: xlwt
